AUTHORS
LICENSE
LICENSE_CVODE
MANIFEST.in
README
RELEASES
gpl-3.0.txt
runswig
setup.cfg
setup.py
STEPS.egg-info/PKG-INFO
STEPS.egg-info/SOURCES.txt
STEPS.egg-info/dependency_links.txt
STEPS.egg-info/top_level.txt
cpp/common.h
cpp/error.cpp
cpp/error.hpp
cpp/geom/comp.cpp
cpp/geom/comp.hpp
cpp/geom/diffboundary.cpp
cpp/geom/diffboundary.hpp
cpp/geom/doxygen.hpp
cpp/geom/geom.cpp
cpp/geom/geom.hpp
cpp/geom/memb.cpp
cpp/geom/memb.hpp
cpp/geom/patch.cpp
cpp/geom/patch.hpp
cpp/geom/tet.cpp
cpp/geom/tet.hpp
cpp/geom/tetmesh.cpp
cpp/geom/tetmesh.hpp
cpp/geom/tetmesh_rw.cpp
cpp/geom/tetmesh_rw.hpp
cpp/geom/tmcomp.cpp
cpp/geom/tmcomp.hpp
cpp/geom/tmpatch.cpp
cpp/geom/tmpatch.hpp
cpp/geom/tri.cpp
cpp/geom/tri.hpp
cpp/math/constants.hpp
cpp/math/doxygen.hpp
cpp/math/ghk.cpp
cpp/math/ghk.hpp
cpp/math/linsolve.cpp
cpp/math/linsolve.hpp
cpp/math/tetrahedron.cpp
cpp/math/tetrahedron.hpp
cpp/math/tools.cpp
cpp/math/tools.hpp
cpp/math/triangle.cpp
cpp/math/triangle.hpp
cpp/model/chan.cpp
cpp/model/chan.hpp
cpp/model/chanstate.cpp
cpp/model/chanstate.hpp
cpp/model/diff.cpp
cpp/model/diff.hpp
cpp/model/doxygen.hpp
cpp/model/ghkcurr.cpp
cpp/model/ghkcurr.hpp
cpp/model/model.cpp
cpp/model/model.hpp
cpp/model/ohmiccurr.cpp
cpp/model/ohmiccurr.hpp
cpp/model/reac.cpp
cpp/model/reac.hpp
cpp/model/spec.cpp
cpp/model/spec.hpp
cpp/model/sreac.cpp
cpp/model/sreac.hpp
cpp/model/surfsys.cpp
cpp/model/surfsys.hpp
cpp/model/vdepsreac.cpp
cpp/model/vdepsreac.hpp
cpp/model/vdeptrans.cpp
cpp/model/vdeptrans.hpp
cpp/model/volsys.cpp
cpp/model/volsys.hpp
cpp/rng/doxygen.hpp
cpp/rng/mt19937.cpp
cpp/rng/mt19937.hpp
cpp/rng/rng.cpp
cpp/rng/rng.hpp
cpp/solver/api.hpp
cpp/solver/api_batchdata.cpp
cpp/solver/api_comp.cpp
cpp/solver/api_diffboundary.cpp
cpp/solver/api_main.cpp
cpp/solver/api_memb.cpp
cpp/solver/api_patch.cpp
cpp/solver/api_recording.cpp
cpp/solver/api_roidata.cpp
cpp/solver/api_tet.cpp
cpp/solver/api_tri.cpp
cpp/solver/api_vert.cpp
cpp/solver/chandef.cpp
cpp/solver/chandef.hpp
cpp/solver/chanstatedef.cpp
cpp/solver/chanstatedef.hpp
cpp/solver/compdef.cpp
cpp/solver/compdef.hpp
